odoo10_addon_hr_expense_operating_unit-10.0.1.0.0-py2.7-nspkg.pth
odoo/addons/hr_expense_operating_unit/README.rst
odoo/addons/hr_expense_operating_unit/__init__.py
odoo/addons/hr_expense_operating_unit/__manifest__.py
odoo/addons/hr_expense_operating_unit/models/__init__.py
odoo/addons/hr_expense_operating_unit/models/hr_expense.py
odoo/addons/hr_expense_operating_unit/security/hr_expense_security.xml
odoo/addons/hr_expense_operating_unit/static/description/icon.png
odoo/addons/hr_expense_operating_unit/tests/__init__.py
odoo/addons/hr_expense_operating_unit/tests/test_hr_expense_operating_unit.py
odoo/addons/hr_expense_operating_unit/views/hr_expense_view.xml
odoo10_addon_hr_expense_operating_unit-10.0.1.0.0.dist-info/DESCRIPTION.rst
odoo10_addon_hr_expense_operating_unit-10.0.1.0.0.dist-info/METADATA
odoo10_addon_hr_expense_operating_unit-10.0.1.0.0.dist-info/RECORD
odoo10_addon_hr_expense_operating_unit-10.0.1.0.0.dist-info/WHEEL
odoo10_addon_hr_expense_operating_unit-10.0.1.0.0.dist-info/metadata.json
odoo10_addon_hr_expense_operating_unit-10.0.1.0.0.dist-info/namespace_packages.txt
odoo10_addon_hr_expense_operating_unit-10.0.1.0.0.dist-info/top_level.txt
